textual_astview/__init__.py
textual_astview/__main__.py
textual_astview/py.typed
textual_astview/app/__init__.py
textual_astview/app/astare.py
textual_astview/app/screens/__init__.py
textual_astview/app/screens/main.py
textual_astview/widgets/__init__.py
textual_astview/widgets/astview.py
textual_astview/widgets/node_info.py
textual_astview/widgets/source.py
textual_astview/widgets/source_info.py
textual_astview-0.8.0.dist-info/LICENCE
textual_astview-0.8.0.dist-info/METADATA
textual_astview-0.8.0.dist-info/WHEEL
textual_astview-0.8.0.dist-info/entry_points.txt
textual_astview-0.8.0.dist-info/top_level.txt
textual_astview-0.8.0.dist-info/RECORD
