Metadata-Version: 2.1
Name: textual-astview
Version: 0.8.0
Summary: An AST viewing widget library plus app, built for and with Textual.
Home-page: https://github.com/davep/textual-astview
Author: Dave Pearson
Author-email: davep@davep.org
Maintainer: Dave Pearson
Maintainer-email: davep@davep.org
License: License :: OSI Approved :: MIT License
Project-URL: Documentation, https://github.com/davep/textual-astview/blob/main/README.md
Project-URL: Source, https://github.com/davep/textual-astview
Project-URL: Issues, https://github.com/davep/textual-astview/issues
Project-URL: Discussions, https://github.com/davep/textual-astview/discussions
Keywords: terminal,library,widget,tool,ast,abstract syntax tree,viewer,explorer
Classifier: License :: OSI Approved :: MIT License
Classifier: Environment :: Console
Classifier: Development Status :: 3 - Alpha
Classifier: Intended Audience :: Developers
Classifier: Operating System :: OS Independent
Classifier: Programming Language :: Python :: 3.8
Classifier: Programming Language :: Python :: 3.9
Classifier: Programming Language :: Python :: 3.10
Classifier: Programming Language :: Python :: 3.11
Classifier: Topic :: Terminals
Classifier: Topic :: Utilities
Classifier: Topic :: Software Development :: Libraries
Classifier: Typing :: Typed
Requires-Python: >=3.8
License-File: LICENCE
Requires-Dist: textual >=0.39.0
Requires-Dist: textual-fspicker >=0.0.10
